<?xml version="1.0"?>
<root><timestamp>2024-09-06 12:02:23:847</timestamp><level>ELECTORAL-DISTRICT</level><ed_code>19</ed_code><ed_name>Badulla</ed_name><by_party><candidate><party_code>IND1</party_code><votes>0</votes><percentage>0</percentage><party_name>Independent Candidate 1</party_name><candidate>AKMEEMANA DAYARATHANA THERO</candidate></candidate><candidate><party_code>DUA</party_code><votes>0</votes><percentage>0</percentage><party_name>Democratic Unity Alliance</party_name><candidate>ABUBAKAR MOHAMED INFAS</candidate></candidate><candidate><party_code>IND2</party_code><votes>0</votes><percentage>0</percentage><party_name>Independent Candidate 2</party_name><candidate>SIRIPALA AMARASINGHE</candidate></candidate><candidate><party_code>IND3</party_code><votes>0</votes><percentage>0</percentage><party_name>Independent Candidate 3</party_name><candidate>IDROOS MOHAMED ILLIAS</candidate></candidate><candidate><party_code>IND4</party_code><votes>0</votes><percentage>0</percentage><party_name>Independent Candidate 4</party_name><candidate>K.K. PIYADASA</candidate></candidate><candidate><party_code>IND5</party_code><votes>0</votes><percentage>0</percentage><party_name>Independent Candidate 5</party_name><candidate>SARATH KEERTHIRATHNA</candidate></candidate><candidate><party_code>IND6</party_code><votes>0</votes><percentage>0</percentage><party_name>Independent Candidate 6</party_name><candidate>K.A. KULARATNA</candidate></candidate><candidate><party_code>APP</party_code><votes>0</votes><percentage>0</percentage><party_name>Arunalu Peoples Alliance</party_name><candidate>K.R. KRISHAN</candidate></candidate><candidate><party_code>IND7</party_code><votes>0</votes><percentage>0</percentage><party_name>Independent Candidate 7</party_name><candidate>PALLIMULLA KAPUGAMAGE ANURA SIDNEY JAYARATHNA</candidate></candidate><candidate><party_code>SLCP</party_code><votes>0</votes><percentage>0</percentage><party_name>Communist Party of Sri Lanka </party_name><candidate>DILITH JAYAWEERA</candidate></candidate><candidate><party_code>USP</party_code><votes>0</votes><percentage>0</percentage><party_name>United Socialist Party</party_name><candidate>SIRITUNGA JAYASURIYA</candidate></candidate><candidate><party_code>IND8</party_code><votes>0</votes><percentage>0</percentage><party_name>Independent Candidate 8</party_name><candidate>MYLVAGANAM THILAKARAJAH</candidate></candidate><candidate><party_code>DUNF</party_code><votes>0</votes><percentage>0</percentage><party_name>Democratic United National Front</party_name><candidate>AGAMPODI PRASANGA SURANJEEWA ANOJ DE SILVA</candidate></candidate><candidate><party_code>UNFF</party_code><votes>0</votes><percentage>0</percentage><party_name>United National Freedom Front</party_name><candidate>LALITH DE SILVA</candidate></candidate><candidate><party_code>RJA</party_code><votes>0</votes><percentage>0</percentage><party_name>Ruhunu Janatha Alliance</party_name><candidate>AJANTHA DE ZOYSA</candidate></candidate><candidate><party_code>NPP</party_code><votes>0</votes><percentage>0</percentage><party_name>Jathika Jana Balawegaya</party_name><candidate>ANURA KUMARA DISSANAYAKE</candidate></candidate><candidate><party_code>SLSP</party_code><votes>0</votes><percentage>0</percentage><party_name>Socialist Party of Sri Lanka</party_name><candidate>MAHINDA DEWAGE</candidate></candidate><candidate><party_code>IND9</party_code><votes>0</votes><percentage>0</percentage><party_name>Independent Candidate 9</party_name><candidate>ARIYANETHIRAN PAKKIYASELVAM</candidate></candidate><candidate><party_code>IND10</party_code><votes>0</votes><percentage>0</percentage><party_name>Independent Candidate 10</party_name><candidate>VICTOR PERERA</candidate></candidate><candidate><party_code>IND11</party_code><votes>0</votes><percentage>0</percentage><party_name>Independent Candidate 11</party_name><candidate>ANURUDDHA POLGAMPALA</candidate></candidate><candidate><party_code>SJB</party_code><votes>0</votes><percentage>0</percentage><party_name>Samagi Jana Balawegaya</party_name><candidate>SAJITH PREMADASA</candidate></candidate><candidate><party_code>IND12</party_code><votes>0</votes><percentage>0</percentage><party_name>Independent Candidate 12</party_name><candidate>SARATH FONSEKA</candidate></candidate><candidate><party_code>IND13</party_code><votes>0</votes><percentage>0</percentage><party_name>Independent Candidate 13</party_name><candidate>DISSANAYAKA MUDIYANSELAGE BANDARANAYAKE</candidate></candidate><candidate><party_code>NDF</party_code><votes>0</votes><percentage>0</percentage><party_name>Jathika Sangwardhena Peramuna</party_name><candidate>SARATH BANDARANAYAKE</candidate></candidate><candidate><party_code>JSP</party_code><votes>0</votes><percentage>0</percentage><party_name>Jana Setha Peramuna</party_name><candidate>BATHTHARAMULLE SEELARATHANA THERO</candidate></candidate><candidate><party_code>SPF</party_code><votes>0</votes><percentage>0</percentage><party_name>Socialist People Forum</party_name><candidate>NUWAN BOPEGE</candidate></candidate><candidate><party_code>NSU</party_code><votes>0</votes><percentage>0</percentage><party_name>Nawa Sihala Urumaya</party_name><candidate>SARATH MANAMENDRA</candidate></candidate><candidate><party_code>IND14</party_code><votes>0</votes><percentage>0</percentage><party_name>Independent Candidate 14</party_name><candidate>PEMASIRI MANAGE</candidate></candidate><candidate><party_code>IND15</party_code><votes>0</votes><percentage>0</percentage><party_name>Independent Candidate 15</party_name><candidate>ANURUDDHA ROSHAN RANASINGHE</candidate></candidate><candidate><party_code>ELPP</party_code><votes>0</votes><percentage>0</percentage><party_name>Eksath Lanka Podujana Pakshaya</party_name><candidate>JANAKA RATNAYAKE</candidate></candidate><candidate><party_code>SBP</party_code><votes>0</votes><percentage>0</percentage><party_name>Samabima Party</party_name><candidate>NAMAL RAJAPAKSHA</candidate></candidate><candidate><party_code>SLPP</party_code><votes>0</votes><percentage>0</percentage><party_name>Sri Lanka Podujana Peramuna</party_name><candidate>NAMAL RAJAPAKSA</candidate></candidate><candidate><party_code>JPF</party_code><votes>0</votes><percentage>0</percentage><party_name>National Democratic Front</party_name><candidate>WIJEYADASA RAJAPAKSHE</candidate></candidate><candidate><party_code>SLLP</party_code><votes>0</votes><percentage>0</percentage><party_name>Sri Lanka Labour Party</party_name><candidate>A.S.P. LIYANAGE</candidate></candidate><candidate><party_code>AJP</party_code><votes>0</votes><percentage>0</percentage><party_name>Ape Janabala Pakshaya</party_name><candidate>KEERTHIE WICKRAMARATNE</candidate></candidate><candidate><party_code>NSSP</party_code><votes>0</votes><percentage>0</percentage><party_name>Nawa Sama Samaja Party</party_name><candidate>PRIYANTHA WICKRAMASINGHE</candidate></candidate><candidate><party_code>IND16</party_code><votes>0</votes><percentage>0</percentage><party_name>Independent Candidate 16</party_name><candidate>RANIL WICKREMESINGHE</candidate></candidate><candidate><party_code>SEP</party_code><votes>0</votes><percentage>0</percentage><party_name>Socialist Equality Party</party_name><candidate>PANI WIJESIRIWARDENA</candidate></candidate><candidate><party_code>NIF</party_code><votes>0</votes><percentage>0</percentage><party_name>New Independent Front</party_name><candidate>OSHALA HERATH</candidate></candidate></by_party><summary><valid>0</valid><rejected>0</rejected><polled>0</polled><electors>0</electors><percent_valid>0</percent_valid><percent_rejected>0</percent_rejected><percent_polled>0</percent_polled></summary><type>PRESIDENTIAL-FIRST</type><sequence_number>0010</sequence_number><reference>116740282</reference></root>
